govee_lan_control/__init__.py
govee_lan_control/discover.py
govee_lan_control/govee_lan_device.py
govee_lan_control/udp.py
govee_lan_control-1.0.3.dist-info/LICENSE
govee_lan_control-1.0.3.dist-info/METADATA
govee_lan_control-1.0.3.dist-info/WHEEL
govee_lan_control-1.0.3.dist-info/top_level.txt
govee_lan_control-1.0.3.dist-info/RECORD
