Metadata-Version: 2.1
Name: govee_lan_control
Version: 1.0.3
Summary: A Python package to control Govee LED devices over the local network using multicast UDP packets.
Home-page: https://github.com/srinivasansharath/govee_lan_control
Author: Sharath Srinivasan
Author-email: srinivasansharath@gmail.com
License: MIT
Classifier: Programming Language :: Python :: 3
Classifier: License :: OSI Approved :: MIT License
Classifier: Operating System :: OS Independent
Requires-Python: >=3.6
License-File: LICENSE
